notutils/__init__.py
notutils/notutils.py
notutils-0.0.1.dist-info/METADATA
notutils-0.0.1.dist-info/WHEEL
notutils-0.0.1.dist-info/entry_points.txt
notutils-0.0.1.dist-info/top_level.txt
notutils-0.0.1.dist-info/RECORD
