Metadata-Version: 2.1
Name: notutils
Version: 0.0.1
Summary: Notebook utilities.
Home-page: https://github.com/lawrennd/notutils
Author: Neil D. Lawrence
Author-email: lawrennd@gmail.com
License: MIT
Platform: UNKNOWN
Classifier: License :: OSI Approved :: MIT License
Classifier: Programming Language :: Python
Classifier: Programming Language :: Python :: 3
Classifier: Programming Language :: Python :: 3.6
Classifier: Programming Language :: Python :: Implementation :: CPython
Classifier: Programming Language :: Python :: Implementation :: PyPy
Requires-Python: >=3.6.0
Requires-Dist: IPython
